mlip_jax/__init__.py
mlip_jax/dummy_file.txt
mlip_jax/dummy_script.py
mlip_jax/data/__init__.py
mlip_jax/data/chemical_system.py
mlip_jax/data/configs.py
mlip_jax/data/dataset_info.py
mlip_jax/data/graph_dataset_builder.py
mlip_jax/data/chemical_systems_readers/__init__.py
mlip_jax/data/chemical_systems_readers/chemical_systems_reader.py
mlip_jax/data/chemical_systems_readers/combined_reader.py
mlip_jax/data/chemical_systems_readers/extxyz_reader.py
mlip_jax/data/chemical_systems_readers/hdf5_reader.py
mlip_jax/data/chemical_systems_readers/type_aliases.py
mlip_jax/data/chemical_systems_readers/utils.py
mlip_jax/data/helpers/__init__.py
mlip_jax/data/helpers/atomic_energies.py
mlip_jax/data/helpers/atomic_number_table.py
mlip_jax/data/helpers/data_prefetching.py
mlip_jax/data/helpers/data_split.py
mlip_jax/data/helpers/dummy_init_graph.py
mlip_jax/data/helpers/dynamically_batch.py
mlip_jax/data/helpers/edge_vectors.py
mlip_jax/data/helpers/graph_creation.py
mlip_jax/data/helpers/graph_dataset.py
mlip_jax/data/helpers/neighbor_analysis.py
mlip_jax/data/helpers/neighborhood.py
mlip_jax/inference/__init__.py
mlip_jax/inference/batched_inference.py
mlip_jax/models/__init__.py
mlip_jax/models/atomic_energies.py
mlip_jax/models/blocks.py
mlip_jax/models/force_field.py
mlip_jax/models/loss.py
mlip_jax/models/loss_helpers.py
mlip_jax/models/mlip_network.py
mlip_jax/models/model_io.py
mlip_jax/models/options.py
mlip_jax/models/params_loading.py
mlip_jax/models/params_transfer.py
mlip_jax/models/predictor.py
mlip_jax/models/radial_embedding.py
mlip_jax/models/mace/blocks.py
mlip_jax/models/mace/config.py
mlip_jax/models/mace/message_passing.py
mlip_jax/models/mace/models.py
mlip_jax/models/mace/symmetric_contraction.py
mlip_jax/models/nequip/config.py
mlip_jax/models/nequip/models.py
mlip_jax/models/nequip/nequip_helpers.py
mlip_jax/models/visnet/blocks.py
mlip_jax/models/visnet/config.py
mlip_jax/models/visnet/models.py
mlip_jax/simulation/__init__.py
mlip_jax-0.1.4.dist-info/METADATA
mlip_jax-0.1.4.dist-info/WHEEL
mlip_jax-0.1.4.dist-info/licenses/LICENSE
mlip_jax-0.1.4.dist-info/RECORD
